ipython_oidc_client/__init__.py
ipython_oidc_client/client/main.js
ipython_oidc_client/server/__init__.py
ipython_oidc_client/server/static/redirect.html
ipython_oidc_client-0.1.3.dist-info/LICENSE
ipython_oidc_client-0.1.3.dist-info/WHEEL
ipython_oidc_client-0.1.3.dist-info/METADATA
ipython_oidc_client-0.1.3.dist-info/RECORD
