Metadata-Version: 2.1
Name: ipython_oidc_client
Version: 0.1.3
Summary: A Jupyter extension to perform OAuth2 flows (e.g. token, code) in notebooks.
Home-page: https://github.com/jorgecarleitao/ipython-oidc-client
License: UNKNOWN
Author: Jorge C. Leitao
Author-email: jorgecarleitao@gmail.com
Classifier: License :: OSI Approved :: MIT License
